kollibri/__init__.py
kollibri/__main__.py
kollibri/cli.py
kollibri/kollibri.py
kollibri-1.0.0.data/scripts/kollibri
kollibri-1.0.0.dist-info/licenses/LICENSE.txt
kollibri-1.0.0.dist-info/METADATA
kollibri-1.0.0.dist-info/WHEEL
kollibri-1.0.0.dist-info/top_level.txt
kollibri-1.0.0.dist-info/zip-safe
kollibri-1.0.0.dist-info/RECORD
