Metadata-Version: 2.4
Name: kollibri
Version: 1.0.0
Summary: Extract collocations from VERT data
Home-page: https://gitlab.uzh.ch/corpus-linguistic-uzh/kollibri
Author: Danny McDonald, Sonja Huber
Author-email: noah.bubenhofer@ds.uzh.ch
License: MIT
Keywords: corpus,linguistics,corpora,collocation,vert
License-File: LICENSE.txt
Requires-Dist: tqdm
Dynamic: author
Dynamic: author-email
Dynamic: description
Dynamic: description-content-type
Dynamic: home-page
Dynamic: keywords
Dynamic: license
Dynamic: license-file
Dynamic: requires-dist
Dynamic: summary
